sksurgeryspeech/__init__.py
sksurgeryspeech/__main__.py
sksurgeryspeech/_version.py
sksurgeryspeech/algorithms/__init__.py
sksurgeryspeech/algorithms/voice_recognition_service.py
sksurgeryspeech/ui/__init__.py
sksurgeryspeech/ui/sksurgeryspeech_command_line.py
sksurgeryspeech/ui/sksurgeryspeech_demo.py
scikit_surgeryspeech-0.2.0.dist-info/LICENSE
scikit_surgeryspeech-0.2.0.dist-info/METADATA
scikit_surgeryspeech-0.2.0.dist-info/WHEEL
scikit_surgeryspeech-0.2.0.dist-info/entry_points.txt
scikit_surgeryspeech-0.2.0.dist-info/top_level.txt
scikit_surgeryspeech-0.2.0.dist-info/RECORD
