Metadata-Version: 2.1
Name: scikit-surgeryspeech
Version: 0.2.0
Summary: Interface to speech services for image-guided surgery.
Home-page: https://weisslab.cs.ucl.ac.uk/WEISS/SoftwareRepositories/SNAPPY/scikit-surgeryspeech
Author: Matt Clarkson
Author-email: YOUR-EMAIL@ucl.ac.uk
License: BSD-3 license
Keywords: medical imaging
Platform: UNKNOWN
Classifier: Development Status :: 3 - Alpha
Classifier: Intended Audience :: Developers
Classifier: Intended Audience :: Healthcare Industry
Classifier: Intended Audience :: Information Technology
Classifier: Intended Audience :: Science/Research
Classifier: License :: OSI Approved :: BSD License
Classifier: Programming Language :: Python
Classifier: Programming Language :: Python :: 2
Classifier: Programming Language :: Python :: 3
Classifier: Topic :: Scientific/Engineering :: Information Analysis
Classifier: Topic :: Scientific/Engineering :: Medical Science Apps.
Requires-Dist: pyaudio
Requires-Dist: SpeechRecognition
Requires-Dist: google-api-python-client
Requires-Dist: oauth2client
Requires-Dist: PySide2
Requires-Dist: scikit-surgerycore
Requires-Dist: pvporcupine
